censorship/__init__.py
censorship/censure.py
censorship/tools.py
censorship.py-0.16.dist-info/METADATA
censorship.py-0.16.dist-info/WHEEL
censorship.py-0.16.dist-info/top_level.txt
censorship.py-0.16.dist-info/RECORD
