Metadata-Version: 2.1
Name: censorship.py
Version: 0.16
Summary: Censorship Audio is a Python library that allows you to censor specific words in an audio file based on a given list of words.
Author: NestorDante
Author-email: nestor.d.urdaneta@gmail.com
Requires-Dist: pydub
Requires-Dist: sentence-transformers
Requires-Dist: faster-whisper
